src/__init__.py
src/main.py
src/utils/__init__.py
src/utils/config.py
src/utils/db.py
src/utils/types.py
iflow_mcp_tibiritabara_mcp_demo-0.1.0.dist-info/METADATA
iflow_mcp_tibiritabara_mcp_demo-0.1.0.dist-info/WHEEL
iflow_mcp_tibiritabara_mcp_demo-0.1.0.dist-info/entry_points.txt
iflow_mcp_tibiritabara_mcp_demo-0.1.0.dist-info/RECORD
