Metadata-Version: 2.4
Name: iflow-mcp_tibiritabara_mcp-demo
Version: 0.1.0
Summary: Model Context Protocol Demo
Author-email: Ricardo Santos <ricardo.santos.diaz@gmail.com>
Requires-Python: >=3.12
Requires-Dist: mcp[cli]>=1.5.0
Requires-Dist: psycopg[binary,pool]>=3.2.6
Requires-Dist: pydantic-settings>=2.8.1
Requires-Dist: pydantic>=2.10.6
